{
  "metadataAttributes": {
    "section": {
      "value": {
        "type": "STRING",
        "stringValue": "Supercopy"
      },
      "includeForEmbedding": true
    },
    "title": {
      "value": {
        "type": "STRING",
        "stringValue": "Privilege Cards"
      },
      "includeForEmbedding": true
    },
    "source_url": {
      "value": {
        "type": "STRING",
        "stringValue": "https://redhawks.sharepoint.com/sites/Intranet-CampusServices/SitePages/Privilege-Cards.aspx"
      },
      "includeForEmbedding": false
    },
    "tags": {
      "value": {
        "type": "STRING",
        "stringValue": "Privilege Card, Copy Card, vendor, guest, access"
      },
      "includeForEmbedding": true
    }
  }
}